pear/__init__.py
pear/__main__.py
pear_aur-1.2.dist-info/DESCRIPTION.rst
pear_aur-1.2.dist-info/METADATA
pear_aur-1.2.dist-info/RECORD
pear_aur-1.2.dist-info/WHEEL
pear_aur-1.2.dist-info/entry_points.txt
pear_aur-1.2.dist-info/metadata.json
pear_aur-1.2.dist-info/top_level.txt
