Metadata-Version: 2.0
Name: pear-aur
Version: 1.2
Summary: A stupidly simple aur helper
Home-page: https://github.com/philipdexter/pear
Author: Philip Dexter
Author-email: philip.dexter@gmail.com
License: Unlicense
Download-URL: https://github.com/philipdexter/pear/tarball/1.2
Keywords: aur,arch linux
Platform: UNKNOWN
Requires-Dist: click
